atomiccreate/__init__.py
atomiccreate-0.3.0.dist-info/DESCRIPTION.rst
atomiccreate-0.3.0.dist-info/METADATA
atomiccreate-0.3.0.dist-info/RECORD
atomiccreate-0.3.0.dist-info/WHEEL
atomiccreate-0.3.0.dist-info/metadata.json
atomiccreate-0.3.0.dist-info/top_level.txt
